srcdit/__init__.py
srcdit/srcdit.py
srcdit-0.1.12.data/scripts/srcdit.py
srcdit-0.1.12.dist-info/LICENSE
srcdit-0.1.12.dist-info/METADATA
srcdit-0.1.12.dist-info/WHEEL
srcdit-0.1.12.dist-info/entry_points.txt
srcdit-0.1.12.dist-info/top_level.txt
srcdit-0.1.12.dist-info/RECORD
