Metadata-Version: 2.1
Name: srcdit
Version: 0.1.12
Summary: Edit and source dotfiles directly from the terminal
Author: Arpit J
Maintainer: Arpit J
Classifier: Programming Language :: Python :: 3
Classifier: License :: OSI Approved :: MIT License
Classifier: Operating System :: OS Independent
Requires-Python: >=3.12
License-File: LICENSE
